solve360-0.9.2.dist-info/top_level.txt
solve360-0.9.2.dist-info/WHEEL
solve360-0.9.2.dist-info/METADATA
solve360-0.9.2.dist-info/RECORD
solve360-0.9.2.dist-info/metadata.json
solve360-0.9.2.dist-info/DESCRIPTION.rst
solve360/tests.py
solve360/__init__.py
solve360/solve360.py
