Metadata-Version: 1.1
Name: solve360
Version: 0.9.2
Summary: Solve360 API Python wrapper
Home-page: https://github.com/nibon/solve360
Author: Daniel Nibon
Author-email: daniel@nibon.se
License: The MIT Licence
Keywords: norada solve360 api wrapper
Platform: UNKNOWN
Classifier: Development Status :: 4 - Beta
Classifier: Intended Audience :: Developers
Classifier: Natural Language :: English
Classifier: Programming Language :: Python :: 2.7
Classifier: Programming Language :: Python :: 3.4
